imio.smartweb.core-1.4.24-py3.12-nspkg.pth
imio/smartweb/core/__init__.py
imio/smartweb/core/config.py
imio/smartweb/core/configure.zcml
imio/smartweb/core/indexers.py
imio/smartweb/core/indexers.zcml
imio/smartweb/core/interfaces.py
imio/smartweb/core/overrides.zcml
imio/smartweb/core/permissions.zcml
imio/smartweb/core/profiles.zcml
imio/smartweb/core/setuphandlers.py
imio/smartweb/core/subscribers.py
imio/smartweb/core/subscribers.zcml
imio/smartweb/core/testing.py
imio/smartweb/core/testing.zcml
imio/smartweb/core/utils.py
imio/smartweb/core/vocabularies.py
imio/smartweb/core/vocabularies.zcml
imio/smartweb/core/behaviors/__init__.py
imio/smartweb/core/behaviors/categorization.py
imio/smartweb/core/behaviors/configure.zcml
imio/smartweb/core/behaviors/listing.py
imio/smartweb/core/behaviors/minisite.py
imio/smartweb/core/behaviors/new_tab.py
imio/smartweb/core/behaviors/orientation.py
imio/smartweb/core/behaviors/quickaccess.py
imio/smartweb/core/behaviors/subsite.py
imio/smartweb/core/browser/__init__.py
imio/smartweb/core/browser/anysurfer.py
imio/smartweb/core/browser/configure.zcml
imio/smartweb/core/browser/controlpanel.py
imio/smartweb/core/browser/controlpanel_siteadmin.py
imio/smartweb/core/browser/forms.py
imio/smartweb/core/browser/gdpr.py
imio/smartweb/core/browser/icons.py
imio/smartweb/core/browser/layout.py
imio/smartweb/core/browser/redirect_to_main_react_view.py
imio/smartweb/core/browser/sitemap.py
imio/smartweb/core/browser/utils.py
imio/smartweb/core/browser/vocabulary.py
imio/smartweb/core/browser/banner/__init__.py
imio/smartweb/core/browser/banner/configure.zcml
imio/smartweb/core/browser/banner/settings.py
imio/smartweb/core/browser/dashboards/__init__.py
imio/smartweb/core/browser/dashboards/configure.zcml
imio/smartweb/core/browser/dashboards/plausible.pt
imio/smartweb/core/browser/dashboards/plausible.py
imio/smartweb/core/browser/faceted/__init__.py
imio/smartweb/core/browser/faceted/block_view.pt
imio_smartweb_core-1.4.24.dist-info/licenses/LICENSE.GPL
imio_smartweb_core-1.4.24.dist-info/licenses/LICENSE.rst
imio_smartweb_core-1.4.24.dist-info/METADATA
imio_smartweb_core-1.4.24.dist-info/WHEEL
imio_smartweb_core-1.4.24.dist-info/namespace_packages.txt
imio_smartweb_core-1.4.24.dist-info/top_level.txt
imio_smartweb_core-1.4.24.dist-info/RECORD
