Metadata-Version: 2.4
Name: imio.smartweb.core
Version: 1.4.24
Summary: Core product for iMio websites
Home-page: https://github.com/imio/imio.smartweb.core
Author: Christophe Boulanger
Author-email: christophe.boulanger@imio.be
License: GPL version 2
Project-URL: PyPI, https://pypi.python.org/pypi/imio.smartweb.core
Project-URL: Source, https://github.com/imio/imio.smartweb.core
Project-URL: Tracker, https://github.com/imio/imio.smartweb.core/issues
Keywords: Python Plone CMS
Classifier: Development Status :: 5 - Production/Stable
Classifier: Environment :: Web Environment
Classifier: Framework :: Plone
Classifier: Framework :: Plone :: Addon
Classifier: Framework :: Plone :: 6.0
Classifier: Framework :: Plone :: 6.1
Classifier: Programming Language :: Python
Classifier: Programming Language :: Python :: 3
Classifier: Programming Language :: Python :: 3.10
Classifier: Programming Language :: Python :: 3.11
Classifier: Programming Language :: Python :: 3.12
Classifier: Programming Language :: Python :: 3.13
Classifier: Operating System :: OS Independent
Classifier: License :: OSI Approved :: GNU General Public License v2 (GPLv2)
Requires-Python: >=3.10
License-File: LICENSE.GPL
License-File: LICENSE.rst
Requires-Dist: setuptools
Requires-Dist: z3c.jbot
Requires-Dist: z3c.unconfigure
Requires-Dist: plone.api>=1.8.4
Requires-Dist: plone.app.discussion
Requires-Dist: plone.gallery
Requires-Dist: plone.restapi
Requires-Dist: plone.app.dexterity
Requires-Dist: plone.app.imagecropping
Requires-Dist: eea.facetednavigation
Requires-Dist: collective.anysurfer
Requires-Dist: collective.autopublishing
Requires-Dist: collective.faceted.map
Requires-Dist: collective.geolocationbehavior
Requires-Dist: collective.instancebehavior
Requires-Dist: collective.messagesviewlet
Requires-Dist: collective.sendinblue
Requires-Dist: collective.solr
Requires-Dist: collective.taxonomy
Requires-Dist: collective.z3cform.datagridfield
Requires-Dist: embeddify
Requires-Dist: more-itertools
Requires-Dist: imio.smartweb.common
Requires-Dist: imio.smartweb.locales
Provides-Extra: test
Requires-Dist: mock; extra == "test"
Requires-Dist: plone.app.testing; extra == "test"
Requires-Dist: plone.testing>=5.0.0; extra == "test"
Requires-Dist: plone.app.contenttypes; extra == "test"
Requires-Dist: plone.app.robotframework[debug]; extra == "test"
Requires-Dist: plone.restapi[test]; extra == "test"
Requires-Dist: requests-mock; extra == "test"
Requires-Dist: beautifulsoup4; extra == "test"
Requires-Dist: freezegun; extra == "test"
Dynamic: author
Dynamic: author-email
Dynamic: classifier
Dynamic: description
Dynamic: home-page
Dynamic: keywords
Dynamic: license
Dynamic: license-file
Dynamic: project-url
Dynamic: provides-extra
Dynamic: requires-dist
Dynamic: requires-python
Dynamic: summary
